driver_khawasu/__init__.py
driver_khawasu/driver.py
driver_khawasu/common/action.py
driver_khawasu/common/device.py
driver_khawasu-0.0.2.dist-info/LICENSE
driver_khawasu-0.0.2.dist-info/METADATA
driver_khawasu-0.0.2.dist-info/WHEEL
driver_khawasu-0.0.2.dist-info/top_level.txt
driver_khawasu-0.0.2.dist-info/RECORD
