Metadata-Version: 2.1
Name: driver-khawasu
Version: 0.0.2
Summary: Driver for Khawasu
Author-email: Ameharu <me@ameha.ru>
Project-URL: Homepage, https://github.com/khawasu/python_driver
Project-URL: Bug Tracker, https://github.com/khawasu/python_driver/issues
Classifier: Programming Language :: Python :: 3
Classifier: License :: OSI Approved :: MIT License
Classifier: Operating System :: OS Independent
Classifier: Development Status :: 5 - Production/Stable
Requires-Python: >=3.7
License-File: LICENSE
Requires-Dist: msgpack
